MANIFEST.in
setup.py
version.py
src/hashedassets/RELEASE-VERSION
src/hashedassets/__init__.py
src/hashedassets/errors.rst
src/hashedassets/hashedassets.rst
src/hashedassets/regressions.rst
src/hashedassets/rewrite.py
src/hashedassets/serializer.py
src/hashedassets/tests.py
src/hashedassets.egg-info/PKG-INFO
src/hashedassets.egg-info/SOURCES.txt
src/hashedassets.egg-info/dependency_links.txt
src/hashedassets.egg-info/entry_points.txt
src/hashedassets.egg-info/namespace_packages.txt
src/hashedassets.egg-info/not-zip-safe
src/hashedassets.egg-info/requires.txt
src/hashedassets.egg-info/top_level.txt