Metadata-Version: 1.0
Name: hashedassets
Version: 0.3.1
Summary: Copies files to filenames based on their contents
Home-page: http://www.python.org/pypi/hashedassets
Author: Filip Noetzel
Author-email: filip+pypi@j03.de
License: Beerware
Platform: UNKNOWN
Classifier: Programming Language :: Python
Classifier: Programming Language :: Python :: 3
Classifier: Development Status :: 4 - Beta
Classifier: Environment :: Other Environment
Classifier: Intended Audience :: Developers
Classifier: Operating System :: OS Independent
Classifier: Topic :: Software Development :: Libraries :: Python Modules
